{
  "year": "2024",
  "term": "1학기",
  "college": "비분류",
  "department": "비분류",
  "major": "비분류",
  "courses": [
    {
      "order": 1,
      "target_year": "전학년",
      "course_type": "교양선택",
      "course_code": 932001,
      "course_name": "중국어 I",
      "section": 1,
      "credit": 3,
      "grade_type": "Grade",
      "foreign_course": null,
      "instructor_name": "이선옥",
      "class_time": [
        {
          "day": "목",
          "times": [
            "02",
            "03",
            "04"
          ],
          "location": "N14-702(56-702)"
        }
      ],
      "lecture_hours": 3,
      "lecture_times": 3,
      "lab_hours": 0,
      "lab_times": 0,
      "pre_enrollment_count": 4,
      "capacity": 45,
      "enrolled_count": 42,
      "category": "국제화"
    },
    {
      "order": 2,
      "target_year": "전학년",
      "course_type": "교양선택",
      "course_code": 932001,
      "course_name": "중국어 I",
      "section": 3,
      "credit": 3,
      "grade_type": "Grade",
      "foreign_course": null,
      "instructor_name": "조현국",
      "class_time": [
        {
          "day": "금",
          "times": [
            "02",
            "03",
            "04"
          ],
          "location": "N16-1-123(58-123)"
        }
      ],
      "lecture_hours": 3,
      "lecture_times": 3,
      "lab_hours": 0,
      "lab_times": 0,
      "pre_enrollment_count": 10,
      "capacity": 45,
      "enrolled_count": 24,
      "category": "국제화"
    },
    {
      "order": 3,
      "target_year": "전학년",
      "course_type": "교양선택",
      "course_code": 932003,
      "course_name": "독일어I",
      "section": 1,
      "credit": 3,
      "grade_type": "Grade",
      "foreign_course": null,
      "instructor_name": "정수정",
      "class_time": [
        {
          "day": "수",
          "times": [
            "07",
            "08",
            "09"
          ],
          "location": "N16-1-123(58-123)"
        }
      ],
      "lecture_hours": 3,
      "lecture_times": 3,
      "lab_hours": 0,
      "lab_times": 0,
      "pre_enrollment_count": 13,
      "capacity": 40,
      "enrolled_count": 39,
      "category": "국제화"
    },
    {
      "order": 4,
      "target_year": "전학년",
      "course_type": "교양선택",
      "course_code": 932005,
      "course_name": "프랑스어I",
      "section": 1,
      "credit": 3,
      "grade_type": "Grade",
      "foreign_course": null,
      "instructor_name": "김대영",
      "class_time": [
        {
          "day": "월",
          "times": [
            "06",
            "07",
            "08"
          ],
          "location": "N16-1-329(58-329)"
        }
      ],
      "lecture_hours": 3,
      "lecture_times": 3,
      "lab_hours": 0,
      "lab_times": 0,
      "pre_enrollment_count": 10,
      "capacity": 45,
      "enrolled_count": 37,
      "category": "국제화"
    },
    {
      "order": 5,
      "target_year": "전학년",
      "course_type": "교양선택",
      "course_code": 932005,
      "course_name": "프랑스어I",
      "section": 2,
      "credit": 3,
      "grade_type": "Grade",
      "foreign_course": null,
      "instructor_name": "김서영",
      "class_time": [
        {
          "day": "목",
          "times": [
            "07",
            "08",
            "09"
          ],
          "location": "N16-1-123(58-123)"
        }
      ],
      "lecture_hours": 3,
      "lecture_times": 3,
      "lab_hours": 0,
      "lab_times": 0,
      "pre_enrollment_count": 7,
      "capacity": 45,
      "enrolled_count": 36,
      "category": "국제화"
    },
    {
      "order": 6,
      "target_year": "전학년",
      "course_type": "교양선택",
      "course_code": 932007,
      "course_name": "러시아어I",
      "section": 1,
      "credit": 3,
      "grade_type": "Grade",
      "foreign_course": null,
      "instructor_name": "김문황",
      "class_time": [
        {
          "day": "수",
          "times": [
            "02",
            "03",
            "04"
          ],
          "location": "N16-1-329(58-329)"
        }
      ],
      "lecture_hours": 3,
      "lecture_times": 3,
      "lab_hours": 0,
      "lab_times": 0,
      "pre_enrollment_count": 6,
      "capacity": 70,
      "enrolled_count": 37,
      "category": "국제화"
    },
    {
      "order": 7,
      "target_year": "전학년",
      "course_type": "교양선택",
      "course_code": 932012,
      "course_name": "글로벌 문화와 지역학",
      "section": 1,
      "credit": 3,
      "grade_type": "Grade",
      "foreign_course": null,
      "instructor_name": "박미령",
      "class_time": [
        {
          "day": "수",
          "times": [
            "06",
            "07",
            "08"
          ],
          "location": "N14-208(56-208)"
        }
      ],
      "lecture_hours": 3,
      "lecture_times": 3,
      "lab_hours": 0,
      "lab_times": 0,
      "pre_enrollment_count": 22,
      "capacity": 80,
      "enrolled_count": 80,
      "category": "국제화"
    },
    {
      "order": 8,
      "target_year": "전학년",
      "course_type": "교양선택",
      "course_code": 932013,
      "course_name": "글로벌 음식문화와 생활문화",
      "section": 1,
      "credit": 3,
      "grade_type": "Grade",
      "foreign_course": null,
      "instructor_name": "이상오",
      "class_time": [
        {
          "day": "수",
          "times": [
            "06",
            "07",
            "08"
          ],
          "location": "N14-102(56-102)"
        }
      ],
      "lecture_hours": 3,
      "lecture_times": 3,
      "lab_hours": 0,
      "lab_times": 0,
      "pre_enrollment_count": 130,
      "capacity": 80,
      "enrolled_count": 75,
      "category": "국제화"
    },
    {
      "order": 9,
      "target_year": "전학년",
      "course_type": "교양선택",
      "course_code": 932013,
      "course_name": "글로벌 음식문화와 생활문화",
      "section": 2,
      "credit": 3,
      "grade_type": "Grade",
      "foreign_course": null,
      "instructor_name": "이상오",
      "class_time": [
        {
          "day": "목",
          "times": [
            "06",
            "07",
            "08"
          ],
          "location": "N14-207(56-207)"
        }
      ],
      "lecture_hours": 3,
      "lecture_times": 3,
      "lab_hours": 0,
      "lab_times": 0,
      "pre_enrollment_count": 134,
      "capacity": 80,
      "enrolled_count": 80,
      "category": "국제화"
    },
    {
      "order": 10,
      "target_year": "전학년",
      "course_type": "교양선택",
      "course_code": 932014,
      "course_name": "기초일본어",
      "section": 1,
      "credit": 2,
      "grade_type": "Grade",
      "foreign_course": null,
      "instructor_name": "권동현",
      "class_time": [
        {
          "day": "화",
          "times": [
            "01",
            "02"
          ],
          "location": "N14-106(56-106)"
        }
      ],
      "lecture_hours": 2,
      "lecture_times": 2,
      "lab_hours": 0,
      "lab_times": 0,
      "pre_enrollment_count": 26,
      "capacity": 70,
      "enrolled_count": 48,
      "category": "국제화"
    },
    {
      "order": 11,
      "target_year": "전학년",
      "course_type": "교양선택",
      "course_code": 932014,
      "course_name": "기초일본어",
      "section": 2,
      "credit": 2,
      "grade_type": "Grade",
      "foreign_course": null,
      "instructor_name": "강지연",
      "class_time": [
        {
          "day": "금",
          "times": [
            "02",
            "03"
          ],
          "location": "N14-208(56-208)"
        }
      ],
      "lecture_hours": 2,
      "lecture_times": 2,
      "lab_hours": 0,
      "lab_times": 0,
      "pre_enrollment_count": 35,
      "capacity": 70,
      "enrolled_count": 64,
      "category": "국제화"
    },
    {
      "order": 12,
      "target_year": "전학년",
      "course_type": "교양선택",
      "course_code": 932015,
      "course_name": "영어청취력",
      "section": 1,
      "credit": 3,
      "grade_type": "Grade",
      "foreign_course": null,
      "instructor_name": "김순배",
      "class_time": [
        {
          "day": "화",
          "times": [
            "01",
            "02",
            "03"
          ],
          "location": "N16-1-226(58-226)"
        }
      ],
      "lecture_hours": 3,
      "lecture_times": 3,
      "lab_hours": 0,
      "lab_times": 0,
      "pre_enrollment_count": 4,
      "capacity": 40,
      "enrolled_count": 41,
      "category": "국제화"
    },
    {
      "order": 13,
      "target_year": "전학년",
      "course_type": "교양선택",
      "course_code": 932016,
      "course_name": "영어회화",
      "section": 1,
      "credit": 3,
      "grade_type": "Grade",
      "foreign_course": null,
      "instructor_name": "데일 마르셀",
      "class_time": [
        {
          "day": "금",
          "times": [
            "01",
            "02",
            "03"
          ],
          "location": "N16-1-226(58-226)"
        }
      ],
      "lecture_hours": 3,
      "lecture_times": 3,
      "lab_hours": 0,
      "lab_times": 0,
      "pre_enrollment_count": 10,
      "capacity": 40,
      "enrolled_count": 15,
      "category": "국제화"
    },
    {
      "order": 14,
      "target_year": "전학년",
      "course_type": "교양선택",
      "course_code": 932017,
      "course_name": "실용영문법",
      "section": 1,
      "credit": 3,
      "grade_type": "Grade",
      "foreign_course": null,
      "instructor_name": "박성은",
      "class_time": [
        {
          "day": "목",
          "times": [
            "04",
            "05",
            "06"
          ],
          "location": "N14-306(56-306)"
        }
      ],
      "lecture_hours": 3,
      "lecture_times": 3,
      "lab_hours": 0,
      "lab_times": 0,
      "pre_enrollment_count": 0,
      "capacity": 30,
      "enrolled_count": 31,
      "category": "국제화"
    },
    {
      "order": 15,
      "target_year": "전학년",
      "course_type": "교양선택",
      "course_code": 932018,
      "course_name": "토익 듣기와 읽기",
      "section": 1,
      "credit": 3,
      "grade_type": "Grade",
      "foreign_course": null,
      "instructor_name": "윤봉이",
      "class_time": [
        {
          "day": "화",
          "times": [
            "01",
            "02",
            "03"
          ],
          "location": "N14-203(56-203)"
        }
      ],
      "lecture_hours": 3,
      "lecture_times": 3,
      "lab_hours": 0,
      "lab_times": 0,
      "pre_enrollment_count": 19,
      "capacity": 50,
      "enrolled_count": 46,
      "category": "국제화"
    },
    {
      "order": 16,
      "target_year": "전학년",
      "course_type": "교양선택",
      "course_code": 932018,
      "course_name": "토익 듣기와 읽기",
      "section": 2,
      "credit": 3,
      "grade_type": "Grade",
      "foreign_course": null,
      "instructor_name": "윤봉이",
      "class_time": [
        {
          "day": "수",
          "times": [
            "01",
            "02",
            "03"
          ],
          "location": "N14-203(56-203)"
        }
      ],
      "lecture_hours": 3,
      "lecture_times": 3,
      "lab_hours": 0,
      "lab_times": 0,
      "pre_enrollment_count": 44,
      "capacity": 50,
      "enrolled_count": 48,
      "category": "국제화"
    },
    {
      "order": 17,
      "target_year": "전학년",
      "course_type": "교양선택",
      "course_code": 932018,
      "course_name": "토익 듣기와 읽기",
      "section": 3,
      "credit": 3,
      "grade_type": "Grade",
      "foreign_course": null,
      "instructor_name": "심지영",
      "class_time": [
        {
          "day": "월",
          "times": [
            "01",
            "02",
            "03"
          ],
          "location": "N14-108(56-108)"
        }
      ],
      "lecture_hours": 3,
      "lecture_times": 3,
      "lab_hours": 0,
      "lab_times": 0,
      "pre_enrollment_count": 13,
      "capacity": 50,
      "enrolled_count": 50,
      "category": "국제화"
    },
    {
      "order": 18,
      "target_year": "전학년",
      "course_type": "교양선택",
      "course_code": 932022,
      "course_name": "집중 TOPIK II",
      "section": 1,
      "credit": 3,
      "grade_type": "Grade",
      "foreign_course": null,
      "instructor_name": "지주연",
      "class_time": [
        {
          "day": "금",
          "times": [
            "02",
            "03",
            "04"
          ],
          "location": "N14-203(56-203)"
        }
      ],
      "lecture_hours": 3,
      "lecture_times": 3,
      "lab_hours": 0,
      "lab_times": 0,
      "pre_enrollment_count": 9,
      "capacity": 50,
      "enrolled_count": 49,
      "category": "국제화"
    },
    {
      "order": 19,
      "target_year": "전학년",
      "course_type": "교양선택",
      "course_code": 932024,
      "course_name": "충북지역문화와 동아시아 문화교류",
      "section": 1,
      "credit": 3,
      "grade_type": "Grade",
      "foreign_course": null,
      "instructor_name": "김호진",
      "class_time": [
        {
          "day": "목",
          "times": [
            "07",
            "08",
            "09"
          ],
          "location": "N18-112(64-112)"
        }
      ],
      "lecture_hours": 3,
      "lecture_times": 3,
      "lab_hours": 0,
      "lab_times": 0,
      "pre_enrollment_count": 10,
      "capacity": 100,
      "enrolled_count": 97,
      "category": "국제화"
    },
    {
      "order": 20,
      "target_year": "전학년",
      "course_type": "교양선택",
      "course_code": 932027,
      "course_name": "국제개발협력의 이해",
      "section": 1,
      "credit": 3,
      "grade_type": "Grade",
      "foreign_course": null,
      "instructor_name": "송양훈",
      "class_time": [
        {
          "day": "토",
          "times": [
            "01",
            "02",
            "03"
          ],
          "location": "가상강의실1"
        }
      ],
      "lecture_hours": 3,
      "lecture_times": 3,
      "lab_hours": 0,
      "lab_times": 0,
      "pre_enrollment_count": 23,
      "capacity": 50,
      "enrolled_count": 43,
      "category": "국제화"
    }
  ]
}